python_package/__init__.py
python_package/setup.py
quantum_cryptocurrency_miner-1.0.0.dist-info/licenses/LICENSE
quantum_cryptocurrency_miner-1.0.0.dist-info/licenses/Notice of Filing.PDF
quantum_cryptocurrency_miner-1.0.0.dist-info/METADATA
quantum_cryptocurrency_miner-1.0.0.dist-info/WHEEL
quantum_cryptocurrency_miner-1.0.0.dist-info/entry_points.txt
quantum_cryptocurrency_miner-1.0.0.dist-info/top_level.txt
quantum_cryptocurrency_miner-1.0.0.dist-info/RECORD
