Metadata-Version: 2.4
Name: quantum-cryptocurrency-miner
Version: 1.0.0
Summary: Next-generation quantum cryptocurrency mining system with distributed architecture
Home-page: https://github.com/quantum-miner/quantum-cryptocurrency-miner
Author: Quantum Miner Team
Author-email: team@quantum-miner.com
Project-URL: Bug Reports, https://github.com/quantum-miner/quantum-cryptocurrency-miner/issues
Project-URL: Source, https://github.com/quantum-miner/quantum-cryptocurrency-miner
Project-URL: Documentation, https://quantum-miner.readthedocs.io/
Classifier: Development Status :: 5 - Production/Stable
Classifier: Intended Audience :: Developers
Classifier: Intended Audience :: Financial and Insurance Industry
Classifier: Topic :: Office/Business :: Financial
Classifier: Topic :: Scientific/Engineering :: Physics
Classifier: Topic :: System :: Distributed Computing
Classifier: License :: OSI Approved :: MIT License
Classifier: Programming Language :: Python :: 3
Classifier: Programming Language :: Python :: 3.11
Classifier: Operating System :: OS Independent
Requires-Python: >=3.11
License-File: LICENSE
License-File: Notice of Filing.PDF
Requires-Dist: asyncio==3.4.3
Requires-Dist: aria-cli[full]
Requires-Dist: cryptography==41.0.7
Requires-Dist: grpcio==1.59.0
Requires-Dist: grpcio-tools==1.59.0
Requires-Dist: jsonschema==4.19.2
Requires-Dist: numpy==1.24.3
Requires-Dist: psutil==5.9.6
Requires-Dist: psycopg2-binary==2.9.9
Requires-Dist: redis==5.0.1
Requires-Dist: requests==2.31.0
Requires-Dist: sqlite3
Requires-Dist: threading
Requires-Dist: uuid
Requires-Dist: hashlib
Requires-Dist: hmac
Requires-Dist: secrets
Requires-Dist: base64
Requires-Dist: datetime
Requires-Dist: decimal
Requires-Dist: pathlib
Requires-Dist: logging
Requires-Dist: signal
Requires-Dist: sys
Requires-Dist: time
Requires-Dist: json
Requires-Dist: tempfile
Requires-Dist: os
Requires-Dist: subprocess
Requires-Dist: threading
Requires-Dist: collections
Requires-Dist: heapq
Requires-Dist: dataclasses
Requires-Dist: enum
Requires-Dist: typing
Provides-Extra: dev
Requires-Dist: pytest>=7.0.0; extra == "dev"
Requires-Dist: pytest-asyncio>=0.21.0; extra == "dev"
Requires-Dist: pytest-cov>=4.0.0; extra == "dev"
Requires-Dist: black>=23.0.0; extra == "dev"
Requires-Dist: flake8>=6.0.0; extra == "dev"
Requires-Dist: mypy>=1.0.0; extra == "dev"
Provides-Extra: monitoring
Requires-Dist: prometheus-client>=0.17.0; extra == "monitoring"
Requires-Dist: grafana-api>=1.0.3; extra == "monitoring"
Provides-Extra: quantum
Requires-Dist: qiskit>=0.44.0; extra == "quantum"
Requires-Dist: cirq>=1.2.0; extra == "quantum"
Requires-Dist: pennylane>=0.32.0; extra == "quantum"
Dynamic: author
Dynamic: author-email
Dynamic: classifier
Dynamic: description
Dynamic: description-content-type
Dynamic: home-page
Dynamic: license-file
Dynamic: project-url
Dynamic: provides-extra
Dynamic: requires-dist
Dynamic: requires-python
Dynamic: summary
